{
	"highscores": {
		"world": "Vunira",
		"category": "experience",
		"vocation": "sorcerers",
		"highscore_list": [
			{
				"rank": 1,
				"name": "Heinzinki",
				"vocation": "Master Sorcerer",
				"world": "Vunira",
				"level": 1862,
				"value": 107335727351
			},
			{
				"rank": 2,
				"name": "Epus",
				"vocation": "Master Sorcerer",
				"world": "Vunira",
				"level": 1819,
				"value": 100126256153
			},
			{
				"rank": 3,
				"name": "Drgawki",
				"vocation": "Master Sorcerer",
				"world": "Vunira",
				"level": 1598,
				"value": 67849512298
			},
			{
				"rank": 4,
				"name": "Inferno koox",
				"vocation": "Master Sorcerer",
				"world": "Vunira",
				"level": 1549,
				"value": 61711071918
			},
			{
				"rank": 5,
				"name": "Tatuazyyk",
				"vocation": "Master Sorcerer",
				"world": "Vunira",
				"level": 1515,
				"value": 57739278648
			},
			{
				"rank": 6,
				"name": "Nicol",
				"vocation": "Master Sorcerer",
				"world": "Vunira",
				"level": 1399,
				"value": 45502702115
			},
			{
				"rank": 7,
				"name": "Og Kiedos",
				"vocation": "Master Sorcerer",
				"world": "Vunira",
				"level": 1386,
				"value": 44184038412
			},
			{
				"rank": 8,
				"name": "Byoniic",
				"vocation": "Master Sorcerer",
				"world": "Vunira",
				"level": 1340,
				"value": 40002303604
			},
			{
				"rank": 9,
				"name": "Quakkap",
				"vocation": "Master Sorcerer",
				"world": "Vunira",
				"level": 1293,
				"value": 35919382117
			},
			{
				"rank": 10,
				"name": "Umeex",
				"vocation": "Master Sorcerer",
				"world": "Vunira",
				"level": 1292,
				"value": 35846529590
			},
			{
				"rank": 11,
				"name": "Ykk",
				"vocation": "Master Sorcerer",
				"world": "Vunira",
				"level": 1268,
				"value": 33861678424
			},
			{
				"rank": 12,
				"name": "Daisuki Ito",
				"vocation": "Master Sorcerer",
				"world": "Vunira",
				"level": 1244,
				"value": 31967999735
			},
			{
				"rank": 13,
				"name": "True Hema",
				"vocation": "Master Sorcerer",
				"world": "Vunira",
				"level": 1215,
				"value": 29768432362
			},
			{
				"rank": 14,
				"name": "Grapleer",
				"vocation": "Master Sorcerer",
				"world": "Vunira",
				"level": 1208,
				"value": 29272318565
			},
			{
				"rank": 15,
				"name": "Robin Kint",
				"vocation": "Master Sorcerer",
				"world": "Vunira",
				"level": 1180,
				"value": 27297219454
			},
			{
				"rank": 16,
				"name": "Hardcor",
				"vocation": "Master Sorcerer",
				"world": "Vunira",
				"level": 1172,
				"value": 26718947117
			},
			{
				"rank": 17,
				"name": "Berglin",
				"vocation": "Master Sorcerer",
				"world": "Vunira",
				"level": 1154,
				"value": 25502099791
			},
			{
				"rank": 18,
				"name": "Revanne",
				"vocation": "Master Sorcerer",
				"world": "Vunira",
				"level": 1150,
				"value": 25274729276
			},
			{
				"rank": 19,
				"name": "Rhuor",
				"vocation": "Master Sorcerer",
				"world": "Vunira",
				"level": 1131,
				"value": 23989207320
			},
			{
				"rank": 20,
				"name": "Anna Alexy",
				"vocation": "Master Sorcerer",
				"world": "Vunira",
				"level": 1108,
				"value": 22574355590
			},
			{
				"rank": 21,
				"name": "Illmu",
				"vocation": "Master Sorcerer",
				"world": "Vunira",
				"level": 1092,
				"value": 21604559569
			},
			{
				"rank": 22,
				"name": "Fardar",
				"vocation": "Sorcerer",
				"world": "Vunira",
				"level": 1084,
				"value": 21166399064
			},
			{
				"rank": 23,
				"name": "Lord Zilez",
				"vocation": "Master Sorcerer",
				"world": "Vunira",
				"level": 1083,
				"value": 21066547679
			},
			{
				"rank": 24,
				"name": "Marky Ladd",
				"vocation": "Master Sorcerer",
				"world": "Vunira",
				"level": 1080,
				"value": 20913848091
			},
			{
				"rank": 25,
				"name": "Theuzzito",
				"vocation": "Master Sorcerer",
				"world": "Vunira",
				"level": 1067,
				"value": 20150241855
			},
			{
				"rank": 26,
				"name": "Xilian",
				"vocation": "Master Sorcerer",
				"world": "Vunira",
				"level": 1045,
				"value": 18925002402
			},
			{
				"rank": 27,
				"name": "Saintu",
				"vocation": "Master Sorcerer",
				"world": "Vunira",
				"level": 1044,
				"value": 18864377794
			},
			{
				"rank": 28,
				"name": "Progangus Daxi",
				"vocation": "Master Sorcerer",
				"world": "Vunira",
				"level": 1027,
				"value": 17959397191
			},
			{
				"rank": 29,
				"name": "Minusfour Azilonaccess",
				"vocation": "Master Sorcerer",
				"world": "Vunira",
				"level": 1016,
				"value": 17417471279
			},
			{
				"rank": 30,
				"name": "Horon Aoldas",
				"vocation": "Master Sorcerer",
				"world": "Vunira",
				"level": 1014,
				"value": 17311991164
			},
			{
				"rank": 31,
				"name": "Jessica Aka Snoop",
				"vocation": "Master Sorcerer",
				"world": "Vunira",
				"level": 1011,
				"value": 17147603897
			},
			{
				"rank": 32,
				"name": "Ilimitex",
				"vocation": "Master Sorcerer",
				"world": "Vunira",
				"level": 991,
				"value": 16130440993
			},
			{
				"rank": 33,
				"name": "Weeix",
				"vocation": "Master Sorcerer",
				"world": "Vunira",
				"level": 986,
				"value": 15918271516
			},
			{
				"rank": 34,
				"name": "Tahyaa",
				"vocation": "Master Sorcerer",
				"world": "Vunira",
				"level": 978,
				"value": 15504770290
			},
			{
				"rank": 35,
				"name": "Gustavo Loco",
				"vocation": "Master Sorcerer",
				"world": "Vunira",
				"level": 975,
				"value": 15387245304
			},
			{
				"rank": 36,
				"name": "Alia Goonsquad",
				"vocation": "Master Sorcerer",
				"world": "Vunira",
				"level": 967,
				"value": 14979300888
			},
			{
				"rank": 37,
				"name": "Albi Balbi",
				"vocation": "Master Sorcerer",
				"world": "Vunira",
				"level": 956,
				"value": 14493022333
			},
			{
				"rank": 38,
				"name": "Tito Garci",
				"vocation": "Master Sorcerer",
				"world": "Vunira",
				"level": 955,
				"value": 14427460329
			},
			{
				"rank": 39,
				"name": "Killer Nato",
				"vocation": "Master Sorcerer",
				"world": "Vunira",
				"level": 950,
				"value": 14202263017
			},
			{
				"rank": 40,
				"name": "Dajy",
				"vocation": "Master Sorcerer",
				"world": "Vunira",
				"level": 935,
				"value": 13565652304
			},
			{
				"rank": 41,
				"name": "Jidler",
				"vocation": "Master Sorcerer",
				"world": "Vunira",
				"level": 934,
				"value": 13499349133
			},
			{
				"rank": 42,
				"name": "Anciolka Incognito",
				"vocation": "Master Sorcerer",
				"world": "Vunira",
				"level": 928,
				"value": 13236172575
			},
			{
				"rank": 43,
				"name": "Eu Dei Uh",
				"vocation": "Master Sorcerer",
				"world": "Vunira",
				"level": 927,
				"value": 13199988169
			},
			{
				"rank": 44,
				"name": "Szulcerer",
				"vocation": "Master Sorcerer",
				"world": "Vunira",
				"level": 926,
				"value": 13170465252
			},
			{
				"rank": 45,
				"name": "Rox Fox",
				"vocation": "Master Sorcerer",
				"world": "Vunira",
				"level": 925,
				"value": 13117798219
			},
			{
				"rank": 46,
				"name": "Kardano",
				"vocation": "Master Sorcerer",
				"world": "Vunira",
				"level": 924,
				"value": 13086053454
			},
			{
				"rank": 47,
				"name": "Grzesio rasiak",
				"vocation": "Master Sorcerer",
				"world": "Vunira",
				"level": 912,
				"value": 12569507048
			},
			{
				"rank": 48,
				"name": "Bo Vincencik",
				"vocation": "Master Sorcerer",
				"world": "Vunira",
				"level": 911,
				"value": 12521143477
			},
			{
				"rank": 49,
				"name": "Mighty Rostoverk",
				"vocation": "Master Sorcerer",
				"world": "Vunira",
				"level": 908,
				"value": 12422242378
			},
			{
				"rank": 50,
				"name": "Plusik",
				"vocation": "Master Sorcerer",
				"world": "Vunira",
				"level": 882,
				"value": 11379897016
			}
		],
		"highscore_page": {
			"current_page": 1,
			"total_pages": 20,
			"total_records": 1000
		}
	},
	"information": {
		"api": {
			"version": 4,
			"release": "edge",
			"commit": "f18095ab39c7d88a23a12c2a9441d6882cd46c18"
		},
		"tibia_urls": [
			"https://www.tibia.com/community/?subtopic=highscores&world=Vunira&category=6&profession=4&currentpage=1"
		],
		"status": {
			"http_code": 200
		}
	}
}
