{
	"highscores": {
		"world": "Vunira",
		"category": "experience",
		"vocation": "sorcerers",
		"highscore_list": [
			{
				"rank": 1,
				"name": "Epus",
				"vocation": "Master Sorcerer",
				"world": "Vunira",
				"level": 1703,
				"value": 82152299276
			},
			{
				"rank": 2,
				"name": "Heinzinki",
				"vocation": "Master Sorcerer",
				"world": "Vunira",
				"level": 1633,
				"value": 72365371073
			},
			{
				"rank": 3,
				"name": "Zarmalus",
				"vocation": "Master Sorcerer",
				"world": "Vunira",
				"level": 1377,
				"value": 43366272288
			},
			{
				"rank": 4,
				"name": "Panwierzba",
				"vocation": "Master Sorcerer",
				"world": "Vunira",
				"level": 1365,
				"value": 42204000107
			},
			{
				"rank": 5,
				"name": "Dadizon",
				"vocation": "Master Sorcerer",
				"world": "Vunira",
				"level": 1335,
				"value": 39536994779
			},
			{
				"rank": 6,
				"name": "Gandalf Joe",
				"vocation": "Master Sorcerer",
				"world": "Vunira",
				"level": 1288,
				"value": 35455202364
			},
			{
				"rank": 7,
				"name": "Quakkap",
				"vocation": "Master Sorcerer",
				"world": "Vunira",
				"level": 1279,
				"value": 34718494961
			},
			{
				"rank": 8,
				"name": "Ykk",
				"vocation": "Master Sorcerer",
				"world": "Vunira",
				"level": 1261,
				"value": 33310894602
			},
			{
				"rank": 9,
				"name": "Saiintu",
				"vocation": "Master Sorcerer",
				"world": "Vunira",
				"level": 1251,
				"value": 32512885453
			},
			{
				"rank": 10,
				"name": "Nicol",
				"vocation": "Master Sorcerer",
				"world": "Vunira",
				"level": 1206,
				"value": 29149654405
			},
			{
				"rank": 11,
				"name": "True Hema",
				"vocation": "Master Sorcerer",
				"world": "Vunira",
				"level": 1204,
				"value": 28977427948
			},
			{
				"rank": 12,
				"name": "Og Kiedos",
				"vocation": "Master Sorcerer",
				"world": "Vunira",
				"level": 1186,
				"value": 27689744428
			},
			{
				"rank": 13,
				"name": "Vaparir",
				"vocation": "Master Sorcerer",
				"world": "Vunira",
				"level": 1171,
				"value": 26657739789
			},
			{
				"rank": 14,
				"name": "Hardcor",
				"vocation": "Master Sorcerer",
				"world": "Vunira",
				"level": 1120,
				"value": 23337331877
			},
			{
				"rank": 15,
				"name": "Berglin",
				"vocation": "Master Sorcerer",
				"world": "Vunira",
				"level": 1102,
				"value": 22201370615
			},
			{
				"rank": 16,
				"name": "Daisuki Ito",
				"vocation": "Master Sorcerer",
				"world": "Vunira",
				"level": 1090,
				"value": 21504380028
			},
			{
				"rank": 17,
				"name": "Grapleer",
				"vocation": "Master Sorcerer",
				"world": "Vunira",
				"level": 1083,
				"value": 21070218219
			},
			{
				"rank": 18,
				"name": "Lord Zilez",
				"vocation": "Master Sorcerer",
				"world": "Vunira",
				"level": 1077,
				"value": 20743172117
			},
			{
				"rank": 19,
				"name": "Umeex",
				"vocation": "Master Sorcerer",
				"world": "Vunira",
				"level": 1066,
				"value": 20111296919
			},
			{
				"rank": 20,
				"name": "Byoniic",
				"vocation": "Master Sorcerer",
				"world": "Vunira",
				"level": 1058,
				"value": 19655900936
			},
			{
				"rank": 21,
				"name": "Robin Kint",
				"vocation": "Master Sorcerer",
				"world": "Vunira",
				"level": 1056,
				"value": 19516005013
			},
			{
				"rank": 22,
				"name": "Anna Alexy",
				"vocation": "Master Sorcerer",
				"world": "Vunira",
				"level": 1039,
				"value": 18632082437
			},
			{
				"rank": 23,
				"name": "Dantelix",
				"vocation": "Master Sorcerer",
				"world": "Vunira",
				"level": 1038,
				"value": 18542010758
			},
			{
				"rank": 24,
				"name": "Gunner Konrad",
				"vocation": "Master Sorcerer",
				"world": "Vunira",
				"level": 1037,
				"value": 18527920462
			},
			{
				"rank": 25,
				"name": "Revanne",
				"vocation": "Master Sorcerer",
				"world": "Vunira",
				"level": 1027,
				"value": 17973202588
			},
			{
				"rank": 26,
				"name": "Jessica Aka Snoop",
				"vocation": "Master Sorcerer",
				"world": "Vunira",
				"level": 1006,
				"value": 16873361063
			},
			{
				"rank": 27,
				"name": "Sklejkovvy",
				"vocation": "Master Sorcerer",
				"world": "Vunira",
				"level": 1001,
				"value": 16635994673
			},
			{
				"rank": 28,
				"name": "Legend Sinjestar",
				"vocation": "Master Sorcerer",
				"world": "Vunira",
				"level": 998,
				"value": 16500774691
			},
			{
				"rank": 29,
				"name": "Fardar",
				"vocation": "Master Sorcerer",
				"world": "Vunira",
				"level": 996,
				"value": 16397049576
			},
			{
				"rank": 30,
				"name": "Eme Caesar",
				"vocation": "Master Sorcerer",
				"world": "Vunira",
				"level": 974,
				"value": 15321303635
			},
			{
				"rank": 31,
				"name": "Theuzzika",
				"vocation": "Master Sorcerer",
				"world": "Vunira",
				"level": 971,
				"value": 15187526899
			},
			{
				"rank": 32,
				"name": "Tito Garci",
				"vocation": "Master Sorcerer",
				"world": "Vunira",
				"level": 955,
				"value": 14427460329
			},
			{
				"rank": 33,
				"name": "Eu Dei Uh",
				"vocation": "Master Sorcerer",
				"world": "Vunira",
				"level": 927,
				"value": 13192692344
			},
			{
				"rank": 34,
				"name": "Prezes Flamme",
				"vocation": "Master Sorcerer",
				"world": "Vunira",
				"level": 912,
				"value": 12574512599
			},
			{
				"rank": 35,
				"name": "Mighty Rostoverk",
				"vocation": "Master Sorcerer",
				"world": "Vunira",
				"level": 908,
				"value": 12422242378
			},
			{
				"rank": 36,
				"name": "Bo Vincencik",
				"vocation": "Master Sorcerer",
				"world": "Vunira",
				"level": 905,
				"value": 12275816033
			},
			{
				"rank": 37,
				"name": "Nawalony Mage",
				"vocation": "Master Sorcerer",
				"world": "Vunira",
				"level": 902,
				"value": 12155297749
			},
			{
				"rank": 38,
				"name": "Grzesio rasiak",
				"vocation": "Master Sorcerer",
				"world": "Vunira",
				"level": 898,
				"value": 11991066528
			},
			{
				"rank": 39,
				"name": "Kon Daruhna",
				"vocation": "Master Sorcerer",
				"world": "Vunira",
				"level": 878,
				"value": 11210214793
			},
			{
				"rank": 40,
				"name": "Lutises",
				"vocation": "Master Sorcerer",
				"world": "Vunira",
				"level": 854,
				"value": 10332587707
			},
			{
				"rank": 41,
				"name": "Albi Balbi",
				"vocation": "Master Sorcerer",
				"world": "Vunira",
				"level": 852,
				"value": 10253341807
			},
			{
				"rank": 42,
				"name": "Kapton",
				"vocation": "Master Sorcerer",
				"world": "Vunira",
				"level": 848,
				"value": 10097978072
			},
			{
				"rank": 43,
				"name": "Diemagierin",
				"vocation": "Master Sorcerer",
				"world": "Vunira",
				"level": 844,
				"value": 9955612886
			},
			{
				"rank": 44,
				"name": "Marky",
				"vocation": "Master Sorcerer",
				"world": "Vunira",
				"level": 842,
				"value": 9902249039
			},
			{
				"rank": 45,
				"name": "Rhuar",
				"vocation": "Sorcerer",
				"world": "Vunira",
				"level": 824,
				"value": 9276980593
			},
			{
				"rank": 46,
				"name": "Daamager",
				"vocation": "Master Sorcerer",
				"world": "Vunira",
				"level": 816,
				"value": 9011921568
			},
			{
				"rank": 47,
				"name": "Roffaline",
				"vocation": "Master Sorcerer",
				"world": "Vunira",
				"level": 813,
				"value": 8900301116
			},
			{
				"rank": 48,
				"name": "Spenceron",
				"vocation": "Master Sorcerer",
				"world": "Vunira",
				"level": 807,
				"value": 8717311887
			},
			{
				"rank": 49,
				"name": "Temir",
				"vocation": "Master Sorcerer",
				"world": "Vunira",
				"level": 805,
				"value": 8644490073
			},
			{
				"rank": 50,
				"name": "Beccanlol",
				"vocation": "Master Sorcerer",
				"world": "Vunira",
				"level": 804,
				"value": 8625910628
			}
		],
		"highscore_page": {
			"current_page": 1,
			"total_pages": 20,
			"total_records": 1000
		}
	},
	"information": {
		"api": {
			"version": 4,
			"release": "4.1.2",
			"commit": "3b2501461ec799b6c5ecdc2b49ac446a56f065df"
		},
		"status": {
			"http_code": 200
		}
	}
}
